compile_graph/__init__.py
compile_graph/compile_graph.py
compile_graph/wrapviz.py
compile_graph-0.1.3.dist-info/entry_points.txt
compile_graph-0.1.3.dist-info/LICENSE
compile_graph-0.1.3.dist-info/WHEEL
compile_graph-0.1.3.dist-info/METADATA
compile_graph-0.1.3.dist-info/RECORD
